{
  "generatedAt": "2026-06-14T21:14:27.682Z",
  "ranges": {
    "todayIso": "2026-06-14T07:00:00.000Z",
    "monthIso": "2026-06-01T07:00:00.000Z",
    "nowIso": "2026-06-14T21:13:00.175Z"
  },
  "today": {
    "contacts": 3,
    "uniqueCallsAttempted": 0,
    "uniqueTextsSent": 4,
    "uniqueCallsAnswered": 0,
    "uniqueTextsResponded": 1,
    "calledContacts": [],
    "textedContacts": [
      {
        "name": "Tim Smith",
        "texts": 1,
        "responded": false,
        "lastAt": "2026-06-14T18:25:49.368Z"
      },
      {
        "name": "Jhon Brad",
        "texts": 2,
        "responded": false,
        "lastAt": "2026-06-14T17:33:00.433Z"
      },
      {
        "name": "Javier Trujillo",
        "texts": 1,
        "responded": false,
        "lastAt": "2026-06-14T13:35:27.233Z"
      },
      {
        "name": "Luis Cordova",
        "texts": 1,
        "responded": true,
        "lastAt": "2026-06-14T13:28:20.731Z"
      }
    ]
  },
  "mtd": {
    "contacts": 158,
    "uniqueCallsAttempted": 139,
    "uniqueTextsSent": 858,
    "uniqueCallsAnswered": 37,
    "uniqueTextsResponded": 108
  },
  "daily": [
    {
      "date": "2026-06-01",
      "uniqueCallsAttempted": 0,
      "uniqueTextsSent": 2,
      "uniqueCallsAnswered": 0,
      "uniqueTextsResponded": 1
    },
    {
      "date": "2026-06-02",
      "uniqueCallsAttempted": 0,
      "uniqueTextsSent": 4,
      "uniqueCallsAnswered": 0,
      "uniqueTextsResponded": 0
    },
    {
      "date": "2026-06-03",
      "uniqueCallsAttempted": 17,
      "uniqueTextsSent": 15,
      "uniqueCallsAnswered": 3,
      "uniqueTextsResponded": 2
    },
    {
      "date": "2026-06-04",
      "uniqueCallsAttempted": 12,
      "uniqueTextsSent": 17,
      "uniqueCallsAnswered": 5,
      "uniqueTextsResponded": 4
    },
    {
      "date": "2026-06-05",
      "uniqueCallsAttempted": 19,
      "uniqueTextsSent": 17,
      "uniqueCallsAnswered": 4,
      "uniqueTextsResponded": 6
    },
    {
      "date": "2026-06-06",
      "uniqueCallsAttempted": 0,
      "uniqueTextsSent": 15,
      "uniqueCallsAnswered": 0,
      "uniqueTextsResponded": 4
    },
    {
      "date": "2026-06-07",
      "uniqueCallsAttempted": 0,
      "uniqueTextsSent": 21,
      "uniqueCallsAnswered": 0,
      "uniqueTextsResponded": 4
    },
    {
      "date": "2026-06-08",
      "uniqueCallsAttempted": 31,
      "uniqueTextsSent": 45,
      "uniqueCallsAnswered": 10,
      "uniqueTextsResponded": 16
    },
    {
      "date": "2026-06-09",
      "uniqueCallsAttempted": 16,
      "uniqueTextsSent": 29,
      "uniqueCallsAnswered": 3,
      "uniqueTextsResponded": 7
    },
    {
      "date": "2026-06-10",
      "uniqueCallsAttempted": 24,
      "uniqueTextsSent": 43,
      "uniqueCallsAnswered": 7,
      "uniqueTextsResponded": 13
    },
    {
      "date": "2026-06-11",
      "uniqueCallsAttempted": 0,
      "uniqueTextsSent": 30,
      "uniqueCallsAnswered": 0,
      "uniqueTextsResponded": 5
    },
    {
      "date": "2026-06-12",
      "uniqueCallsAttempted": 20,
      "uniqueTextsSent": 598,
      "uniqueCallsAnswered": 5,
      "uniqueTextsResponded": 45
    },
    {
      "date": "2026-06-13",
      "uniqueCallsAttempted": 0,
      "uniqueTextsSent": 18,
      "uniqueCallsAnswered": 0,
      "uniqueTextsResponded": 0
    },
    {
      "date": "2026-06-14",
      "uniqueCallsAttempted": 0,
      "uniqueTextsSent": 4,
      "uniqueCallsAnswered": 0,
      "uniqueTextsResponded": 1
    }
  ],
  "conversationsScanned": 800
}